tcc_ext/__init__.py
tcc_ext/credentials.py
tencentcloud_sdk_python_ext-0.1.4.dist-info/LICENSE
tencentcloud_sdk_python_ext-0.1.4.dist-info/METADATA
tencentcloud_sdk_python_ext-0.1.4.dist-info/WHEEL
tencentcloud_sdk_python_ext-0.1.4.dist-info/RECORD
