Metadata-Version: 2.1
Name: tencentcloud-sdk-python-ext
Version: 0.1.4
Summary: 腾讯云Python Sdk 插件
Home-page: https://github.com/mingyugg/tencentcloud-sdk-python-ext
License: Apache-2.0
Author: thomas
Author-email: thomas.mingyu.guo@gmail.com
Requires-Python: >=3.7,<4.0
Classifier: License :: OSI Approved :: Apache Software License
Classifier: Programming Language :: Python :: 3
Classifier: Programming Language :: Python :: 3.7
Classifier: Programming Language :: Python :: 3.8
Classifier: Programming Language :: Python :: 3.9
Classifier: Programming Language :: Python :: 3.10
Classifier: Programming Language :: Python :: 3.11
Requires-Dist: tencentcloud-sdk-python-common (>=3.0.1023,<4.0.0)
Project-URL: Repository, https://github.com/mingyugg/tencentcloud-sdk-python-ext
